apple_books_mcp/__init__.py
apple_books_mcp/__main__.py
apple_books_mcp/server.py
mseep_apple_books_mcp-0.1.9.dist-info/licenses/LICENSE
mseep_apple_books_mcp-0.1.9.dist-info/METADATA
mseep_apple_books_mcp-0.1.9.dist-info/WHEEL
mseep_apple_books_mcp-0.1.9.dist-info/entry_points.txt
mseep_apple_books_mcp-0.1.9.dist-info/top_level.txt
mseep_apple_books_mcp-0.1.9.dist-info/RECORD
