Metadata-Version: 2.4
Name: mseep-apple-books-mcp
Version: 0.1.9
Summary: Model Context Protocol (MCP) server for Apple Books
Author-email: mseep <support@skydeck.ai>
License: Apache 2.0
Keywords: apple-books,mcp,model-context-protocol,apple-books-mcp,llm,productivity
Classifier: Development Status :: 4 - Beta
Classifier: Intended Audience :: Developers
Classifier: License :: OSI Approved :: Apache Software License
Classifier: Programming Language :: Python :: 3
Classifier: Programming Language :: Python :: 3.13
Requires-Python: >=3.13
License-File: LICENSE
Requires-Dist: click>=8.1.8
Requires-Dist: fastmcp>=0.4.1
Requires-Dist: py-apple-books>=1.3.0
Dynamic: license-file
